{
    "name":"活动日历",
    "id":"com.rlvrc.vpm",
    "url":"https://mmyo456.github.io/events-calendar/index.json",
    "author":{
        "email":"yaya@qmq.moe",
        "name":"91VRC",
        "url":"https://rlvrc.cn/"
    },
    "description":"以下列表你可以在VCC里使用91VRChat的组件",
    "infoLink":{
        "url":"https://rlvrc.cn/",
        "text":"活动日历官网"
    },
    "bannerUrl":"banner.png",
    "githubRepos":[
        "mmyo456/events-calendar"
    ],
    "packages":[
        {
            "name":"com.rlvrc.cn",
            "releases":[
                "https://i.qmq.moe/vpm/com.rlvrc.cn0.8.4.zip",
                "https://i.qmq.moe/vpm/com.rlvrc.cn0.8.4-dev1.zip",
                "https://i.qmq.moe/vpm/com.rlvrc.cn0.8.41.zip",
                "https://i.qmq.moe/vpm/com.rlvrc.cn0.8.5.zip",
            ]
        }
    ]
}
