{
    "name":"咕咕日历",
    "id":"com.rlvrc.vpm",
    "url":"https://mmyo456.github.io/events-calendar/index.json",
    "author":{
        "email":"oychengjiu@163.com",
        "name":"91VRC",
        "url":"https://rlvrc.cn/"
    },
    "description":"以下列表你可以在VCC里使用91VRChat的组件",
    "infoLink":{
        "url":"https://rlvrc.cn/",
        "text":"咕咕日历"
    },
    "bannerUrl":"banner.png",
    "packages":[
        {
            "name":"com.rlvrc.cn",
            "releases":[
                "https://i.ouo.chat/api/rl/vpm/com.rlvrc.cn0.8.4.zip",
                "https://i.ouo.chat/api/rl/vpm/com.rlvrc.cn0.8.4-dev1.zip",
                "https://i.ouo.chat/api/rl/vpm/com.rlvrc.cn0.8.4-dev2.zip",
                "https://i.ouo.chat/api/rl/vpm/com.rlvrc.cn0.8.5.zip",
                "https://i.ouo.chat/api/rl/vpm/com.rlvrc.cn0.8.6.zip",
                "https://i.ouo.chat/api/rl/vpm/com.rlvrc.cn0.8.7.zip",
                "https://i.ouo.chat/api/rl/vpm/com.rlvrc.cn0.8.8.zip",
                "https://i.ouo.chat/api/rl/vpm/com.rlvrc.cn0.8.9-dev.zip",
                "https://i.ouo.chat/api/rl/vpm/com.rlvrc.cn0.8.9-dev.zip",
                "https://i.ouo.chat/api/rl/vpm/com.rlvrc.cn0.9.0.zip",
                "https://i.ouo.chat/api/rl/vpm/com.rlvrc.cn0.9.1.zip",
                "https://i.ouo.chat/api/rl/vpm/com.rlvrc.cn0.9.2.zip",
            ]
        }
    ]
}
